fastapi_smith/__init__.py
fastapi_smith/cli.py
fastapi_smith/config.py
fastapi_smith/generator.py
fastapi_smith/prompts.py
fastapi_smith/templates/Dockerfile.j2
fastapi_smith/templates/alembic.ini.j2
fastapi_smith/templates/docker-compose.yml.j2
fastapi_smith/templates/env.example.j2
fastapi_smith/templates/gitignore.j2
fastapi_smith/templates/mypy.ini.j2
fastapi_smith/templates/pre-commit-config.yaml.j2
fastapi_smith/templates/pyproject.toml.j2
fastapi_smith/templates/pyrefly.toml.j2
fastapi_smith/templates/readme.md.j2
fastapi_smith/templates/ruff.toml.j2
fastapi_smith/templates/app/config.py.j2
fastapi_smith/templates/app/database.py.j2
fastapi_smith/templates/app/main.py.j2
fastapi_smith/templates/app/admin/views.py.j2
fastapi_smith/templates/app/core/cache.py.j2
fastapi_smith/templates/app/core/health.py.j2
fastapi_smith/templates/app/core/logging.py.j2
fastapi_smith/templates/app/core/rate_limit.py.j2
fastapi_smith/templates/app/core/security.py.j2
fastapi_smith/templates/app/models/base.py.j2
fastapi_smith/templates/app/models/user.py.j2
fastapi_smith/templates/app/routes/auth.py.j2
fastapi_smith/templates/app/routes/users.py.j2
fastapi_smith/templates/app/schemas/user.py.j2
fastapi_smith/templates/app/services/s3.py.j2
fastapi_smith/templates/app/services/ses.py.j2
fastapi_smith/templates/github/ci.yml.j2
fastapi_smith/templates/github/deploy.yml.j2
fastapi_smith/templates/migrations/env.py.j2
fastapi_smith/templates/migrations/script.py.mako.j2
fastapi_smith/templates/tests/conftest.py.j2
fastapi_smith/templates/tests/test_auth.py.j2
fastapi_smith/templates/tests/test_health.py.j2
fastapi_smith-0.2.0.dist-info/METADATA
fastapi_smith-0.2.0.dist-info/WHEEL
fastapi_smith-0.2.0.dist-info/entry_points.txt
fastapi_smith-0.2.0.dist-info/licenses/LICENSE
fastapi_smith-0.2.0.dist-info/RECORD
