Metadata-Version: 2.4
Name: fastapi-smith
Version: 0.2.0
Summary: Interactive CLI to scaffold FastAPI projects with database, auth, admin, and more
Project-URL: Homepage, https://github.com/dhruvbhavsar0612/fastsql-project-setup
Project-URL: Repository, https://github.com/dhruvbhavsar0612/fastsql-project-setup
Project-URL: Documentation, https://dhruvbhavsar0612.github.io/fastsql-project-setup/
Project-URL: Issues, https://github.com/dhruvbhavsar0612/fastsql-project-setup/issues
Project-URL: Changelog, https://github.com/dhruvbhavsar0612/fastsql-project-setup/blob/main/CHANGELOG.md
Author-email: Dhruv Bhavsar <dhruvbhavsar0612@gmail.com>
Maintainer-email: Dhruv Bhavsar <dhruvbhavsar0612@gmail.com>
License: MIT
License-File: LICENSE
Keywords: admin,async,boilerplate,cli,cookiecutter,fastapi,mysql,postgresql,project-generator,scaffold,sqlalchemy,sqlite,template
Classifier: Development Status :: 4 - Beta
Classifier: Environment :: Console
Classifier: Framework :: FastAPI
Classifier: Intended Audience :: Developers
Classifier: License :: OSI Approved :: MIT License
Classifier: Operating System :: OS Independent
Classifier: Programming Language :: Python :: 3
Classifier: Programming Language :: Python :: 3.10
Classifier: Programming Language :: Python :: 3.11
Classifier: Programming Language :: Python :: 3.12
Classifier: Programming Language :: Python :: 3.13
Classifier: Topic :: Internet :: WWW/HTTP :: HTTP Servers
Classifier: Topic :: Software Development :: Code Generators
Classifier: Typing :: Typed
Requires-Python: >=3.10
Requires-Dist: jinja2>=3.1.0
Requires-Dist: questionary>=2.0.0
Requires-Dist: rich>=13.0.0
Requires-Dist: typer>=0.12.0
Provides-Extra: dev
Requires-Dist: mypy>=1.10.0; extra == 'dev'
Requires-Dist: pre-commit>=3.7.0; extra == 'dev'
Requires-Dist: pytest-asyncio>=0.23.0; extra == 'dev'
Requires-Dist: pytest-cov>=5.0.0; extra == 'dev'
Requires-Dist: pytest>=8.0.0; extra == 'dev'
Requires-Dist: ruff>=0.4.0; extra == 'dev'
Provides-Extra: docs
Requires-Dist: mkdocs-material-extensions>=1.3.0; extra == 'docs'
Requires-Dist: mkdocs-material>=9.5.0; extra == 'docs'
Requires-Dist: mkdocs>=1.5.0; extra == 'docs'
